libconeangle/__init__.py
libconeangle/coneangle.py
libconeangle/lib.py
libconeangle/libconeangle.dll
libconeangle/libconeangle.dll.a
libconeangle/typing.py
libconeangle-0.1.2.dist-info/LICENSE
libconeangle-0.1.2.dist-info/LICENSE_bundled.txt
libconeangle-0.1.2.dist-info/METADATA
libconeangle-0.1.2.dist-info/WHEEL
libconeangle-0.1.2.dist-info/top_level.txt
libconeangle-0.1.2.dist-info/RECORD
