Metadata-Version: 2.1
Name: libconeangle
Version: 0.1.2
Summary: Python library for libconeangle
Home-page: https://github.com/kjelljorner/libconeangle
Author: Kjell Jorner
Author-email: kjell.jorner@gmail.com
License: MIT
Classifier: Programming Language :: Python :: 3
Classifier: License :: OSI Approved :: MIT License
Classifier: Operating System :: OS Independent
Requires-Python: >=3.8
License-File: LICENSE
License-File: LICENSE_bundled.txt
